analysis/__main__.py
analysis/as_analysis.py
analysis/as_analysis_sc.py
analysis/compare_ai.py
analysis/count_alleles.py
analysis/count_alleles_sc.py
analysis/filter_data.py
analysis/run_analysis.py
analysis/run_analysis_sc.py
analysis/run_compare_ai.py
counting/__main__.py
counting/count_alleles.py
counting/count_alleles_sc.py
counting/filter_variant_data.py
counting/parse_gene_data.py
counting/run_counting.py
counting/run_counting_sc.py
mapping/__main__.py
mapping/filter_remap_reads.py
mapping/intersect_variant_data.py
mapping/make_remap_reads.py
mapping/remap_utils.py
mapping/remap_utils_optimized.py
mapping/run_mapping.py
mapping/wasp_data_files.py
wasp2/__init__.py
wasp2/cli.py
wasp2/io/__init__.py
wasp2/io/compat.py
wasp2/io/cyvcf2_source.py
wasp2/io/pgen_source.py
wasp2/io/variant_source.py
wasp2/io/vcf_source.py
wasp2-1.3.0.dist-info/METADATA
wasp2-1.3.0.dist-info/WHEEL
wasp2-1.3.0.dist-info/entry_points.txt
wasp2-1.3.0.dist-info/licenses/LICENSE
wasp2_rust/__init__.py
wasp2_rust/wasp2_rust.cpython-311-darwin.so
wasp2-1.3.0.dist-info/RECORD
