Metadata-Version: 2.4
Name: wasp2
Version: 1.3.0
Classifier: Development Status :: 5 - Production/Stable
Classifier: Intended Audience :: Science/Research
Classifier: License :: OSI Approved :: MIT License
Classifier: Operating System :: POSIX :: Linux
Classifier: Operating System :: MacOS
Classifier: Programming Language :: Python :: 3
Classifier: Programming Language :: Python :: 3.10
Classifier: Programming Language :: Python :: 3.11
Classifier: Programming Language :: Python :: 3.12
Classifier: Topic :: Scientific/Engineering :: Bio-Informatics
Classifier: Typing :: Typed
Requires-Dist: numpy>=1.21.0
Requires-Dist: pandas>=1.5.0,<3.0.0
Requires-Dist: polars>=0.19.0
Requires-Dist: scipy>=1.10.0
Requires-Dist: pysam>=0.21.0
Requires-Dist: pybedtools>=0.9.0
Requires-Dist: anndata>=0.8.0,<0.12.0
Requires-Dist: scanpy>=1.9.0
Requires-Dist: typer>=0.9.0
Requires-Dist: rich>=13.0.0
Requires-Dist: pytest-benchmark>=4.0 ; extra == 'benchmark'
Requires-Dist: memory-profiler>=0.61 ; extra == 'benchmark'
Requires-Dist: matplotlib>=3.7.0 ; extra == 'benchmark'
Requires-Dist: seaborn>=0.12.0 ; extra == 'benchmark'
Requires-Dist: cyvcf2>=0.31.0 ; extra == 'cyvcf2'
Requires-Dist: pytest>=7.0 ; extra == 'dev'
Requires-Dist: pytest-cov>=4.0 ; extra == 'dev'
Requires-Dist: pytest-benchmark>=4.0 ; extra == 'dev'
Requires-Dist: memory-profiler>=0.61 ; extra == 'dev'
Requires-Dist: mypy>=1.0 ; extra == 'dev'
Requires-Dist: basedpyright>=1.18.0 ; extra == 'dev'
Requires-Dist: ruff>=0.9.0 ; extra == 'dev'
Requires-Dist: pre-commit>=3.0 ; extra == 'dev'
Requires-Dist: build>=0.10 ; extra == 'dev'
Requires-Dist: twine>=4.0 ; extra == 'dev'
Requires-Dist: maturin>=1.4 ; extra == 'dev'
Requires-Dist: bandit[toml]>=1.8.0 ; extra == 'dev'
Requires-Dist: pip-audit>=2.7.0 ; extra == 'dev'
Requires-Dist: sphinx>=7.0 ; extra == 'docs'
Requires-Dist: pydata-sphinx-theme>=0.15 ; extra == 'docs'
Requires-Dist: sphinx-autodoc-typehints>=1.25 ; extra == 'docs'
Requires-Dist: nbsphinx>=0.9 ; extra == 'docs'
Requires-Dist: myst-parser>=2.0 ; extra == 'docs'
Requires-Dist: sphinx-copybutton>=0.5 ; extra == 'docs'
Requires-Dist: sphinx-design>=0.5 ; extra == 'docs'
Requires-Dist: ipython>=8.0 ; extra == 'docs'
Requires-Dist: pgenlib>=0.90 ; extra == 'plink'
Requires-Dist: maturin>=1.0 ; extra == 'rust'
Provides-Extra: benchmark
Provides-Extra: cyvcf2
Provides-Extra: dev
Provides-Extra: docs
Provides-Extra: plink
Provides-Extra: rust
License-File: LICENSE
Summary: Allele-specific analysis of next-generation sequencing data with high-performance multi-format variant support (VCF/cyvcf2/PGEN)
Keywords: bioinformatics,genomics,allele-specific,ngs,sequencing,wasp,allelic-imbalance,plink2,pgen,vcf,cyvcf2,high-performance
Author: Aaron Ho, McVicker Lab
Author-email: Jeff Jaureguy <jeffpjaureguy@gmail.com>
License: MIT
Requires-Python: >=3.10
Project-URL: Documentation, https://Jaureguy760.github.io/WASP2-final/
Project-URL: Homepage, https://github.com/Jaureguy760/WASP2-final
Project-URL: Issues, https://github.com/Jaureguy760/WASP2-final/issues
Project-URL: Repository, https://github.com/Jaureguy760/WASP2-final
